setup.cfg
setup.py
gaspump/__init__.py
gaspump/enums.py
gaspump/models.py
gasss2.egg-info/PKG-INFO
gasss2.egg-info/SOURCES.txt
gasss2.egg-info/dependency_links.txt
gasss2.egg-info/top_level.txt
gasss2.egg-info/zip-safe