Metadata-Version: 2.1
Name: gasss2
Version: 1.0.1
Summary: Gaspump with slippage
Author-email: tafik47634@merotx.com
